{
  "version": "4.6.2",
  "name": "Combined APT Heatmap - ics-attack",
  "domain": "ics-attack",
  "description": "Techniques used across APT groups in ics-attack",
  "gradient": {
    "colors": [
      "#ffffff",
      "#ff0000"
    ],
    "minValue": 0,
    "maxValue": 4
  },
  "techniques": [
    {
      "techniqueID": "T0817",
      "score": 4,
      "comment": "Used by 4 APT groups"
    },
    {
      "techniqueID": "S0093",
      "score": 1,
      "comment": "Used by 1 APT groups"
    },
    {
      "techniqueID": "T0862",
      "score": 2,
      "comment": "Used by 2 APT groups"
    },
    {
      "techniqueID": "T0852",
      "score": 2,
      "comment": "Used by 2 APT groups"
    },
    {
      "techniqueID": "T0865",
      "score": 4,
      "comment": "Used by 4 APT groups"
    },
    {
      "techniqueID": "T0853",
      "score": 2,
      "comment": "Used by 2 APT groups"
    },
    {
      "techniqueID": "T0859",
      "score": 2,
      "comment": "Used by 2 APT groups"
    },
    {
      "techniqueID": "S0606",
      "score": 1,
      "comment": "Used by 1 APT groups"
    },
    {
      "techniqueID": "T0807",
      "score": 1,
      "comment": "Used by 1 APT groups"
    },
    {
      "techniqueID": "S1010",
      "score": 1,
      "comment": "Used by 1 APT groups"
    },
    {
      "techniqueID": "S0604",
      "score": 1,
      "comment": "Used by 1 APT groups"
    },
    {
      "techniqueID": "S1072",
      "score": 1,
      "comment": "Used by 1 APT groups"
    },
    {
      "techniqueID": "T0819",
      "score": 1,
      "comment": "Used by 1 APT groups"
    },
    {
      "techniqueID": "S0089",
      "score": 1,
      "comment": "Used by 1 APT groups"
    },
    {
      "techniqueID": "S0368",
      "score": 1,
      "comment": "Used by 1 APT groups"
    },
    {
      "techniqueID": "S0607",
      "score": 2,
      "comment": "Used by 2 APT groups"
    },
    {
      "techniqueID": "T0884",
      "score": 1,
      "comment": "Used by 1 APT groups"
    },
    {
      "techniqueID": "S0366",
      "score": 1,
      "comment": "Used by 1 APT groups"
    },
    {
      "techniqueID": "T0869",
      "score": 1,
      "comment": "Used by 1 APT groups"
    },
    {
      "techniqueID": "S0496",
      "score": 2,
      "comment": "Used by 2 APT groups"
    },
    {
      "techniqueID": "S0446",
      "score": 2,
      "comment": "Used by 2 APT groups"
    },
    {
      "techniqueID": "S1009",
      "score": 1,
      "comment": "Used by 1 APT groups"
    },
    {
      "techniqueID": "S0372",
      "score": 1,
      "comment": "Used by 1 APT groups"
    }
  ]
}